{
    "Genres": {
        "Action/Thriller": [
            {
                "Name": "Blood Diamond",
                "Type": "Movie",
                "Year": "2006",
                "Age": 15,
                "Actors": [
                    "Leonardo DiCaprio",
                    "Djimon Hounsou",
                    "Jennifer Connelly"
                ],
                "Director": "Edward Zwick",
                "Description": "A fisherman, a smuggler, and a syndicate of businessmen match wits over the possession of a priceless diamond.",
                "Length": "2h 23min",
                "Cover": "/static/Hannibal/HBL_Complete_Series_Poster.jpg",
                "Files": [
                    {
                        "Name": "Blood Diamond",
                        "File": "/static/Hannibal/Boyzvoice.mp4"
                    }
                ]
            }
        ],
        "Drama": [
            {
                "Name": "Moneyball",
                "Type": "Movie",
                "Year": "2011",
                "Age": 0,
                "Actors": [
                    "Brad Pitt",
                    "Robin Wright",
                    "Jonah Hill"
                ],
                "Director": "Bennett Miller",
                "Description": "Oakland A's general manager Billy Beane's successful attempt to assemble a baseball team on a lean budget by employing computer-generated analysis to acquire new players.",
                "Length": "2h 8min",
                "Cover": "/static/Hannibal/HBL_Complete_Series_Poster.jpg",
                "Files": [
                    {
                        "Name": "Moneyball",
                        "File": "Moneyball.mp4"
                    }
                ]
            }
        ],
        "Crime": [
            {
                "Name": "Hannibal",
                "Type": "Series",
                "Year": "2013-2015",
                "Age": 18,
                "Actors": [
                    "Hugh Dancy",
                    "Mads Mikkelsen",
                    "Caroline Dhavernas"
                ],
                "Director": "Bryan Fuller",
                "Length": "N/A",
                "Description": "Explores the early relationship between renowned psychiatrist Hannibal Lecter and a young FBI criminal profiler who is haunted by his ability to empathize with serial killers.",
                "Cover": "/static/Hannibal/HBL_Complete_Series_Poster.jpg",
                "Files": [
                    {
                        "Name": "Season 1",
                        "Episodes": [
                            {
                                "Name": "Apéritif",
                                "Length": "43min",
                                "File": "Hannibal - S01E01 - Apéritif.mp4"
                            },
                            {
                                "Name": "Amuse-Bouche",
                                "Length": "43min",
                                "File": "Hannibal - S01E02 - Amuse-Bouche.mp4"
                            },
                            {
                                "Name": "Potage",
                                "Length": "43min",
                                "File": "Hannibal - S01E03 - Potage.mp4"
                            },
                            {
                                "Name": "Œuf",
                                "Length": "43min",
                                "File": "Hannibal - S01E04 - Œuf.mp4"
                            },
                            {
                                "Name": "Coquilles",
                                "Length": "43min",
                                "File": "Hannibal - S01E05 - Coquilles.mp4"
                            },
                            {
                                "Name": "Entrée",
                                "Length": "43min",
                                "File": "Hannibal - S01E06 - Entrée.mp4"
                            },
                            {
                                "Name": "Sorbet",
                                "Length": "43min",
                                "File": "Hannibal - S01E07 - Sorbet.mp4"
                            }
                        ]
                    },
                    {
                        "Name": "Season 2",
                        "Episodes": [
                            {
                                "Name": "Fromage",
                                "Length": "43min",
                                "File": "Hannibal - S01E08 - Fromage.mp4"
                            },
                            {
                                "Name": "Trou Normand",
                                "Length": "43min",
                                "File": "Hannibal - S01E09 - Trou Normand.mp4"
                            },
                            {
                                "Name": "Buffet Froid",
                                "Length": "43min",
                                "File": "Hannibal - S01E10 - Buffet Froid.mp4"
                            },
                            {
                                "Name": "Rôti",
                                "Length": "43min",
                                "File": "Hannibal - S01E11 - Rôti.mp4"
                            },
                            {
                                "Name": "Relevés",
                                "Length": "43min",
                                "File": "Hannibal - S01E12 - Relevés.mp4"
                            }
                        ]
                    }
                ]
            }
        ]
    }
}